py3_apollo/__init__.py
py3_apollo/apollo_client.py
py3_apollo_client-1.0.4.dist-info/licenses/LICENSE
py3_apollo_client-1.0.4.dist-info/METADATA
py3_apollo_client-1.0.4.dist-info/WHEEL
py3_apollo_client-1.0.4.dist-info/top_level.txt
py3_apollo_client-1.0.4.dist-info/RECORD
