Metadata-Version: 2.4
Name: py3-apollo-client
Version: 1.0.4
Summary: Python3 Client for Ctrip's Apollo
Author-email: renw <renwei_8080@126.com>
License-Expression: MIT
Project-URL: homepage, https://github.com/renw87/py3-apollo-client
Project-URL: repository, https://github.com/renw87/py3-apollo-client
Keywords: apollo
Requires-Python: >=3.6.0
License-File: LICENSE
Requires-Dist: loguru
Requires-Dist: PyYAML
Dynamic: license-file
